snowplow_tracker/__init__.py
snowplow_tracker/_version.py
snowplow_tracker/emitters.py
snowplow_tracker/payload.py
snowplow_tracker/redis_worker.py
snowplow_tracker/self_describing_json.py
snowplow_tracker/subject.py
snowplow_tracker/timestamp.py
snowplow_tracker/tracker.py
snowplow_tracker/utils.py
snowplow_tracker/test/__init__.py
15five_snowplow_tracker-0.8.156.dist-info/LICENSE-2.0.txt
15five_snowplow_tracker-0.8.156.dist-info/METADATA
15five_snowplow_tracker-0.8.156.dist-info/WHEEL
15five_snowplow_tracker-0.8.156.dist-info/top_level.txt
15five_snowplow_tracker-0.8.156.dist-info/RECORD
