Metadata-Version: 2.1
Name: 15five-snowplow-tracker
Version: 0.8.156
Summary: Snowplow event tracker for Python. Add analytics to your Python and Django apps, webapps and games
Home-page: http://snowplowanalytics.com
Author: Anuj More, Alexander Dean, Fred Blundun
Author-email: support@snowplowanalytics.com
License: Apache License 2.0
Platform: UNKNOWN
Classifier: Development Status :: 5 - Production/Stable
Classifier: Intended Audience :: Developers
Classifier: License :: OSI Approved :: Apache Software License
Classifier: Programming Language :: Python
Classifier: Programming Language :: Python :: 2
Classifier: Programming Language :: Python :: 2.7
Classifier: Programming Language :: Python :: 3
Classifier: Programming Language :: Python :: 3.3
Classifier: Programming Language :: Python :: 3.4
Classifier: Programming Language :: Python :: 3.5
Classifier: Operating System :: OS Independent
Requires-Dist: greenlet (>=0.4.15)
Requires-Dist: requests (>=2.19.1)
Requires-Dist: pycontracts (>=1.7.6)
Requires-Dist: celery (>=4.2.0)
Requires-Dist: gevent (>=1.3.3)
Requires-Dist: redis (>=2.10.6)
Requires-Dist: six (>=1.11.0)
